littlemcmc/__init__.py
littlemcmc/base_hmc.py
littlemcmc/exceptions.py
littlemcmc/hmc.py
littlemcmc/integration.py
littlemcmc/math.py
littlemcmc/nuts.py
littlemcmc/parallel_sampling.py
littlemcmc/quadpotential.py
littlemcmc/report.py
littlemcmc/sampling.py
littlemcmc/step_sizes.py
littlemcmc-0.2.2.dist-info/LICENSE.pymc3.txt
littlemcmc-0.2.2.dist-info/LICENSE.pymc4.txt
littlemcmc-0.2.2.dist-info/LICENSE.txt
littlemcmc-0.2.2.dist-info/METADATA
littlemcmc-0.2.2.dist-info/WHEEL
littlemcmc-0.2.2.dist-info/top_level.txt
littlemcmc-0.2.2.dist-info/RECORD
