Metadata-Version: 2.1
Name: littlemcmc
Version: 0.2.2
Summary: A lightweight and performant implementation of HMC and NUTS in Python, spun out of the PyMC project.
Home-page: https://github.com/eigenfoo/littlemcmc
Author: George Ho
Author-email: mail@eigenfoo.xyz
License: Apache License, Version 2.0
Platform: UNKNOWN
Classifier: Programming Language :: Python
Classifier: Programming Language :: Python :: 3
Classifier: Programming Language :: Python :: 3.6
Classifier: Programming Language :: Python :: 3.7
Classifier: License :: OSI Approved :: Apache Software License
Classifier: Intended Audience :: Science/Research
Classifier: Topic :: Scientific/Engineering
Classifier: Topic :: Scientific/Engineering :: Mathematics
Classifier: Operating System :: OS Independent
Requires-Dist: wheel
Requires-Dist: joblib (>=0.14.1)
Requires-Dist: numpy
Requires-Dist: scipy (>=0.18.1)
Requires-Dist: fastprogress
